graphqllexer/__init__.py
graphqllexer/lexer.py
pygments_graphql_lexer-0.1.0.dist-info/entry_points.txt
pygments_graphql_lexer-0.1.0.dist-info/LICENSE
pygments_graphql_lexer-0.1.0.dist-info/WHEEL
pygments_graphql_lexer-0.1.0.dist-info/METADATA
pygments_graphql_lexer-0.1.0.dist-info/RECORD
