Metadata-Version: 2.1
Name: pygments-graphql-lexer
Version: 0.1.0
Summary: GraphQL lexer for Pygments
License: BSD-3-Clause
Author: Gazorby
Author-email: gazorby@pm.me
Requires-Python: >=3.5,<4.0
Classifier: License :: OSI Approved :: BSD License
Classifier: Programming Language :: Python :: 3
Classifier: Programming Language :: Python :: 3.5
Classifier: Programming Language :: Python :: 3.6
Classifier: Programming Language :: Python :: 3.7
Classifier: Programming Language :: Python :: 3.8
Classifier: Programming Language :: Python :: 3.9
Requires-Dist: Pygments (>=2.7.2,<3.0.0)
